tabatu/__init__.py
tabatu/alterar_juros.py
tabatu/alterar_tabua.py
tabatu/juros_constante.py
tabatu/multiplas_vidas.py
tabatu/multiplos_decrementos.py
tabatu/periodicidade.py
tabatu/premissas.py
tabatu/tabua_base.py
tabatu/typing.py
tabatu/unico_decremento.py
tabatu/core/JurosConstanteCpp.cpp
tabatu/core/JurosConstanteCpp.h
tabatu/core/JurosConstanteCpp.pxd
tabatu/core/JurosInterfaceCpp.cpp
tabatu/core/JurosInterfaceCpp.h
tabatu/core/JurosInterfaceCpp.pxd
tabatu/core/TabuaBaseCpp.cpp
tabatu/core/TabuaBaseCpp.h
tabatu/core/TabuaBaseCpp.pxd
tabatu/core/TabuaCpp.cpp
tabatu/core/TabuaCpp.h
tabatu/core/TabuaCpp.pxd
tabatu/core/TabuaInterfaceCpp.cpp
tabatu/core/TabuaInterfaceCpp.h
tabatu/core/TabuaInterfaceCpp.pxd
tabatu/core/TabuaMDTCpp.cpp
tabatu/core/TabuaMDTCpp.h
tabatu/core/TabuaMDTCpp.pxd
tabatu/core/TabuaMultiplasVidasCpp.cpp
tabatu/core/TabuaMultiplasVidasCpp.h
tabatu/core/TabuaMultiplasVidasCpp.pxd
tabatu/core/__init__.py
tabatu/core/alterar_tabua.cpp
tabatu/core/alterar_tabua.h
tabatu/core/alterar_tabua.pxd
tabatu/core/tabatu_cpp.cp38-win_amd64.pyd
tabatu/core/tabatu_cpp.cpp
tabatu/core/tabatu_cpp.pyx
tabatu-0.3.1.dist-info/LICENSE
tabatu-0.3.1.dist-info/METADATA
tabatu-0.3.1.dist-info/WHEEL
tabatu-0.3.1.dist-info/top_level.txt
tabatu-0.3.1.dist-info/RECORD
