Metadata-Version: 2.1
Name: tabatu
Version: 0.3.1
Summary: Tábuas atuariais em C++ com interface em Python.
Author-email: Vitor Capdeville <vgcapdeville@hotmail.com>
Maintainer-email: Vitor Capdeville <vgcapdeville@hotmail.com>
License: GNU GENERAL PUBLIC LICENSE
Project-URL: Homepage, https://github.com/vitorcapdeville/tabuas-atuariais
Project-URL: Bug Reports, https://github.com/vitorcapdeville/tabuas-atuariais/issues
Project-URL: Source, https://github.com/vitorcapdeville/tabuas-atuariais
Keywords: lifetable,actuary
Requires-Python: >=3.7
License-File: LICENSE
Requires-Dist: numpy
Provides-Extra: dev
Requires-Dist: Cython ; extra == 'dev'
